message_pkg/__init__.py
message_pkg/client.py
message_pkg/server.py
JKinc_message_program-1.0.dist-info/LICENSE
JKinc_message_program-1.0.dist-info/METADATA
JKinc_message_program-1.0.dist-info/WHEEL
JKinc_message_program-1.0.dist-info/top_level.txt
JKinc_message_program-1.0.dist-info/RECORD
