Metadata-Version: 2.1
Name: JKinc-message-program
Version: 1.0
Summary: Encrypted Messaging Program for LAN
Home-page: UNKNOWN
Author: JKinc
Author-email: G.T.H.T.I.A.T.A@gmail.com
License: UNKNOWN
Platform: UNKNOWN
Classifier: Programming Language :: Python :: 3
Requires-Python: >=3.6
